kybra_simple_db/__init__.py
kybra_simple_db/constants.py
kybra_simple_db/context.py
kybra_simple_db/db_engine.py
kybra_simple_db/entity.py
kybra_simple_db/hooks.py
kybra_simple_db/mixins.py
kybra_simple_db/properties.py
kybra_simple_db/py.typed
kybra_simple_db/storage.py
kybra_simple_db/system_time.py
kybra_simple_db-0.6.0.dist-info/licenses/LICENSE
kybra_simple_db-0.6.0.dist-info/METADATA
kybra_simple_db-0.6.0.dist-info/WHEEL
kybra_simple_db-0.6.0.dist-info/top_level.txt
kybra_simple_db-0.6.0.dist-info/RECORD
