Metadata-Version: 2.4
Name: kybra_simple_db
Version: 0.6.0
Summary: A lightweight key-value database written in Python, intended for use with Kybra on the Internet Computer (IC)
Home-page: https://github.com/smart-social-contracts/kybra-simple-db
Author: Smart Social Contracts
Author-email: Smart Social Contracts <contact@smartsocialcontracts.org>
License: MIT License
Project-URL: Homepage, https://github.com/smart-social-contracts/kybra-simple-db
Project-URL: Repository, https://github.com/smart-social-contracts/kybra-simple-db.git
Project-URL: Issues, https://github.com/smart-social-contracts/kybra-simple-db/issues
Keywords: database,key-value,entity,relationship,audit
Classifier: Development Status :: 3 - Alpha
Classifier: Intended Audience :: Developers
Classifier: License :: OSI Approved :: MIT License
Classifier: Operating System :: OS Independent
Classifier: Programming Language :: Python :: 3
Classifier: Programming Language :: Python :: 3.10
Classifier: Topic :: Database
Classifier: Topic :: Software Development :: Libraries :: Python Modules
Requires-Python: >=3.7
License-File: LICENSE
Dynamic: author
Dynamic: home-page
Dynamic: license-file
Dynamic: requires-python
